{
  "products": [
    {
      "nama": "Baju Kaos",
      "deskripsi": "Kaos Cultura dengan material Cotton Combed 24 s yang lembut, tidak panas serta tahan lama\nMaterial terbaik yang nyaman uAntuk digunakan aktifitas harian di iklim tropis.\n\nSIZE CHART\n___\nPANJANG BAJU // LEBAR BAJU\nS : 68 // 48\nM : 70 // 50\nL : 72 // 52\nXL : 74 // 54\nXXL : 76 // 56\n\nCek foto slide 3 untuk detail size chart\nSelisih 1-2 Cm pada produk mungkin terjadi dikarenakan proses pengembangan dan produksi. \n___\n\nSpesifikasi\n- Material Cotton Combed 24 S \n- Perbedaan Warna produk dengan display pada settingan layar monitor / handphone anda dapat terjadi.",
      "hargaBeli": "100000",
      "hargaJual": "120000",
      "stok": "20",
      "urlGambar": "https://encrypted-tbn0.gstatic.com/images?q=tbn:ANd9GcRYgi08f21tpsK_D4wmGgKr1ix7SgkyxboZNHcvgFqnyD9rYGhirDZCSb5KTf1jo_H9Zd8&usqp=CAU",
      "id": 1
    }
  ]
}